langgenius_client/__init__.py
langgenius_client/client.py
langgenius_client-0.1.3.dist-info/LICENSE
langgenius_client-0.1.3.dist-info/METADATA
langgenius_client-0.1.3.dist-info/WHEEL
langgenius_client-0.1.3.dist-info/top_level.txt
langgenius_client-0.1.3.dist-info/RECORD
