Metadata-Version: 2.1
Name: langgenius-client
Version: 0.1.3
Summary: A package for interacting with the LangGenius Service-API
Home-page: https://github.com/langgenius/langgenius-client
Author: LangGenius
Author-email: hello@langgenius.ai
License: MIT
Keywords: langgenius nlp ai language-processing
Classifier: Programming Language :: Python :: 3
Classifier: License :: OSI Approved :: MIT License
Classifier: Operating System :: OS Independent
Requires-Python: >=3.6
License-File: LICENSE
Requires-Dist: requests
